{"chapter": 77, "verse": 1, "english": "I cried unto God with my voice, <i>even</i> unto God with my voice; and he gave ear unto me.", "hebrew": [["ל/מנצח", "Hl/H5329", "HRd/Vprmsa"], ["על", "H5921", "HR"], ["ידיתון", "H3038", "HNp"], ["ידותון", "H3038", "HNp"], ["ל/אסף", "Hl/H623", "HR/Np"], ["מזמור", "H4210", "HNcmsa"], ["קול/י", "H6963", "HNcmsc/Sp1cs"], ["אל", "H413", "HR"], ["אלהים", "H430", "HNcmpa"], ["ו/אצעקה", "Hc/H6817", "HC/Vqh1cs"], ["קול/י", "H6963", "HNcmsc/Sp1cs"], ["אל", "H413", "HR"], ["אלהים", "H430", "HNcmpa"], ["ו/האזין", "Hc/H238", "HC/Vhq3ms"], ["אל/י", "H413", "HR/Sp1cs"]], "header": "¶ To the chief Musician, to Jeduthun, A Psalm of Asaph."}
{"chapter": 77, "verse": 2, "english": "In the day of my trouble I sought the Lord: my sore ran in the night, and ceased not: my soul refused to be comforted.", "hebrew": [["ב/יום", "Hb/H3117", "HR/Ncmsc"], ["צרת/י", "H6869", "HNcfsc/Sp1cs"], ["אדנ/י", "H136", "HNcmpc/Sp1cs"], ["דרשתי", "H1875", "HVqp1cs"], ["יד/י", "H3027", "HNcbsc/Sp1cs"], ["לילה", "H3915", "HNcmsa"], ["נגרה", "H5064", "HVNp3fs"], ["ו/לא", "Hc/H3808", "HC/Tn"], ["תפוג", "H6313", "HVqi3fs"], ["מאנה", "H3985", "HVpp3fs"], ["הנחם", "H5162", "HVNc"], ["נפש/י", "H5315", "HNcbsc/Sp1cs"]], "header": ""}
{"chapter": 77, "verse": 3, "english": "I remembered God, and was troubled: I complained, and my spirit was overwhelmed. Selah.", "hebrew": [["אזכרה", "H2142", "HVqh1cs"], ["אלהים", "H430", "HNcmpa"], ["ו/אהמיה", "Hc/H1993", "HC/Vqh1cs"], ["אשיחה", "H7878", "HVqh1cs"], ["ו/תתעטף", "Hc/H5848", "HC/Vti3fs"], ["רוח/י", "H7307", "HNcbsc/Sp1cs"], ["סלה", "H5542", "HTj"]], "header": ""}
{"chapter": 77, "verse": 4, "english": "Thou holdest mine eyes waking: I am so troubled that I cannot speak.", "hebrew": [["אחזת", "H270", "HVqp2ms"], ["שמרות", "H8109", "HNcfpc"], ["עינ/י", "H5869", "HNcbdc/Sp1cs"], ["נפעמתי", "H6470", "HVNp1cs"], ["ו/לא", "Hc/H3808", "HC/Tn"], ["אדבר", "H1696", "HVpi1cs"]], "header": ""}
{"chapter": 77, "verse": 5, "english": "I have considered the days of old, the years of ancient times.", "hebrew": [["חשבתי", "H2803", "HVpp1cs"], ["ימים", "H3117", "HNcmpa"], ["מ/קדם", "Hm/H6924", "HR/Ncmsa"], ["שנות", "H8141", "HNcfpc"], ["עולמים", "H5769", "HNcmpa"]], "header": ""}
{"chapter": 77, "verse": 6, "english": "I call to remembrance my song in the night: I commune with mine own heart: and my spirit made diligent search.", "hebrew": [["אזכרה", "H2142", "HVqh1cs"], ["נגינת/י", "H5058", "HNcfsc/Sp1cs"], ["ב/לילה", "Hb/H3915", "HRd/Ncmsa"], ["עם", "H5973", "HR"], ["לבב/י", "H3824", "HNcmsc/Sp1cs"], ["אשיחה", "H7878", "HVqh1cs"], ["ו/יחפש", "Hc/H2664", "HC/Vpw3ms"], ["רוח/י", "H7307", "HNcbsc/Sp1cs"]], "header": ""}
{"chapter": 77, "verse": 7, "english": "Will the Lord cast off for ever? and will he be favourable no more?", "hebrew": [["ה/ל/עולמים", "Hd/Hl/H5769", "HTi/R/Ncmpa"], ["יזנח", "H2186", "HVqi3ms"], ["אדנ/י", "H136", "HNcmpc/Sp1cs"], ["ו/לא", "Hc/H3808", "HC/Tn"], ["יסיף", "H3254", "HVhi3ms"], ["ל/רצות", "Hl/H7521", "HR/Vqc"], ["עוד", "H5750", "HD"]], "header": ""}
{"chapter": 77, "verse": 8, "english": "Is his mercy clean gone for ever? doth <i>his</i> promise fail for evermore?", "hebrew": [["ה/אפס", "Hd/H656", "HTi/Vqp3ms"], ["ל/נצח", "Hl/H5331", "HR/Ncmsa"], ["חסד/ו", "H2617", "HNcmsc/Sp3ms"], ["גמר", "H1584", "HVqp3ms"], ["אמר", "H562", "HNcmsa"], ["ל/דר", "Hl/H1755", "HR/Ncmsa"], ["ו/דר", "Hc/H1755", "HC/Ncmsa"]], "header": ""}
{"chapter": 77, "verse": 9, "english": "Hath God forgotten to be gracious? hath he in anger shut up his tender mercies? Selah.", "hebrew": [["ה/שכח", "Hi/H7911", "HTi/Vqp3ms"], ["חנות", "H2589", "HVpc"], ["אל", "H410", "HNcmsa"], ["אם", "H518", "HC"], ["קפץ", "H7092", "HVqp3ms"], ["ב/אף", "Hb/H639", "HR/Ncmsa"], ["רחמי/ו", "H7356", "HNcmpc/Sp3ms"], ["סלה", "H5542", "HTj"]], "header": ""}
{"chapter": 77, "verse": 10, "english": "And I said, This <i>is</i> my infirmity: <i>but I will remember</i> the years of the right hand of the most High.", "hebrew": [["ו/אמר", "Hc/H559", "HC/Vqw1cs"], ["חלות/י", "H2470", "HVqc/Sp1cs"], ["היא", "H1931", "HPp3fs"], ["שנות", "H8141", "HVqc"], ["ימין", "H3225", "HNcfsc"], ["עליון", "H5945", "HAamsa"]], "header": ""}
{"chapter": 77, "verse": 11, "english": "I will remember the works of the LORD: surely I will remember thy wonders of old.", "hebrew": [["אזכיר", "H2142", "HVhi1cs"], ["אזכור", "H2142", "HVqi1cs"], ["מעללי", "H4611", "HNcmpc"], ["יה", "H3050", "HNp"], ["כי", "H3588", "HC"], ["אזכרה", "H2142", "HVqh1cs"], ["מ/קדם", "Hm/H6924", "HR/Ncmsa"], ["פלא/ך", "H6382", "HNcmsc/Sp2ms"]], "header": ""}
{"chapter": 77, "verse": 12, "english": "I will meditate also of all thy work, and talk of thy doings.", "hebrew": [["ו/הגיתי", "Hc/H1897", "HC/Vqq1cs"], ["ב/כל", "Hb/H3605", "HR/Ncmsc"], ["פעל/ך", "H6467", "HNcmsc/Sp2ms"], ["ו/ב/עלילותי/ך", "Hc/Hb/H5949", "HC/R/Ncfpc/Sp2ms"], ["אשיחה", "H7878", "HVqh1cs"]], "header": ""}
{"chapter": 77, "verse": 13, "english": "Thy way, O God, <i>is</i> in the sanctuary: who <i>is so</i> great a God as <i>our</i> God?", "hebrew": [["אלהים", "H430", "HNcmpa"], ["ב/קדש", "Hb/H6944", "HRd/Ncmsa"], ["דרכ/ך", "H1870", "HNcbsc/Sp2ms"], ["מי", "H4310", "HTi"], ["אל", "H410", "HNcmsa"], ["גדול", "H1419", "HAamsa"], ["כ/אלהים", "Hk/H430", "HR/Ncmpa"]], "header": ""}
{"chapter": 77, "verse": 14, "english": "Thou <i>art</i> the God that doest wonders: thou hast declared thy strength among the people.", "hebrew": [["אתה", "H859", "HPp2ms"], ["ה/אל", "Hd/H410", "HTd/Ncmsa"], ["עשה", "H6213", "HVqrmsc"], ["פלא", "H6382", "HNcmsa"], ["הודעת", "H3045", "HVhp2ms"], ["ב/עמים", "Hb/H5971", "HRd/Ncmpa"], ["עז/ך", "H5797", "HNcmsc/Sp2ms"]], "header": ""}
{"chapter": 77, "verse": 15, "english": "Thou hast with <i>thine</i> arm redeemed thy people, the sons of Jacob and Joseph. Selah.", "hebrew": [["גאלת", "H1350", "HVqp2ms"], ["ב/זרוע", "Hb/H2220", "HR/Ncbsa"], ["עמ/ך", "H5971", "HNcmsc/Sp2ms"], ["בני", "H1121", "HNcmpc"], ["יעקב", "H3290", "HNp"], ["ו/יוסף", "Hc/H3130", "HC/Np"], ["סלה", "H5542", "HTj"]], "header": ""}
{"chapter": 77, "verse": 16, "english": "The waters saw thee, O God, the waters saw thee; they were afraid: the depths also were troubled.", "hebrew": [["ראו/ך", "H7200", "HVqp3cp/Sp2ms"], ["מים", "H4325", "HNcmpa"], ["אלהים", "H430", "HNcmpa"], ["ראו/ך", "H7200", "HVqp3cp/Sp2ms"], ["מים", "H4325", "HNcmpa"], ["יחילו", "H2342", "HVqi3mp"], ["אף", "H637", "HTa"], ["ירגזו", "H7264", "HVqi3mp"], ["תהמות", "H8415", "HNcbpa"]], "header": ""}
{"chapter": 77, "verse": 17, "english": "The clouds poured out water: the skies sent out a sound: thine arrows also went abroad.", "hebrew": [["זרמו", "H2229", "HVmp3cp"], ["מים", "H4325", "HNcmpa"], ["עבות", "H5645", "HNcbpa"], ["קול", "H6963", "HNcmsa"], ["נתנו", "H5414", "HVqp3cp"], ["שחקים", "H7834", "HNcmpa"], ["אף", "H637", "HTa"], ["חצצי/ך", "H2687", "HNcmpc/Sp2ms"], ["יתהלכו", "H1980", "HVti3mp"]], "header": ""}
{"chapter": 77, "verse": 18, "english": "The voice of thy thunder <i>was</i> in the heaven: the lightnings lightened the world: the earth trembled and shook.", "hebrew": [["קול", "H6963", "HNcmsc"], ["רעמ/ך", "H7482", "HNcmsc/Sp2ms"], ["ב/גלגל", "Hb/H1534", "HRd/Ncmsa"], ["האירו", "H215", "HVhp3cp"], ["ברקים", "H1300", "HNcmpa"], ["תבל", "H8398", "HNcfsa"], ["רגזה", "H7264", "HVqp3fs"], ["ו/תרעש", "Hc/H7493", "HC/Vqw3fs"], ["ה/ארץ", "Hd/H776", "HTd/Ncbsa"]], "header": ""}
{"chapter": 77, "verse": 19, "english": "Thy way <i>is</i> in the sea, and thy path in the great waters, and thy footsteps are not known.", "hebrew": [["ב/ים", "Hb/H3220", "HRd/Ncmsa"], ["דרכ/ך", "H1870", "HNcbsc/Sp2ms"], ["ו/שבילי/ך", "Hc/H7635", "HC/Ncmpc/Sp2ms"], ["ו/שביל/ך", "Hc/H7635", "HC/Ncmsc/Sp2ms"], ["ב/מים", "Hb/H4325", "HR/Ncmpa"], ["רבים", "H7227", "HAampa"], ["ו/עקבותי/ך", "Hc/H6119", "HC/Ncmpc/Sp2ms"], ["לא", "H3808", "HTn"], ["נדעו", "H3045", "HVNp3cp"]], "header": ""}
{"chapter": 77, "verse": 20, "english": "Thou leddest thy people like a flock by the hand of Moses and Aaron.", "hebrew": [["נחית", "H5148", "HVqp2ms"], ["כ/צאן", "Hk/H6629", "HRd/Ncbsa"], ["עמ/ך", "H5971", "HNcmsc/Sp2ms"], ["ב/יד", "Hb/H3027", "HR/Ncbsc"], ["משה", "H4872", "HNp"], ["ו/אהרן", "Hc/H175", "HC/Np"]], "header": ""}
